Workbook

Sheet ACCUEIL
A1: Bienvenue sur le registre Exhaustif des Objets et Matériaux
A2: Que contient le registre ? | F2: Pourquoi deux pages ? | K2: Comment utiliser le registre ? | P2: Comment ça marche ?
A3: Ce registre contient 2 pages : "VENTES"qui contient l'ensemble des objets pouvant êtres fabriqués au métier à tisser, leur prix recommandé, les matériaux requis, la somme du prix des matériaux. "MATERIAUX" la liste des matériaux utilisés par la couture, les prix d'achats, et le prorata par la quantité | F3: Avoir 2 pages distinctes permet de retrouver plus facilement les objets et permet de structurer les calculs pour une utilisation plus facile | K3: Vous pouvez dans la page "VENTES" utiliser ctrl+f pour effectuer une recherche d'un objet souhaité. Vous pouvez dans la page "MATERIAUX" vérifier les prix de rachat classique | P3: La colonne "Cout de création" reprend les éléments précédents et effectue le calcul avec les prix présents dans la page matériaux en multipliant par la quantité nécessaire pour créer l'objet.
A16: J'espère que ce registre vous sera utile bon jeu à tous ^^
Q18: Réalisé par Ja'Zidir
Q20: Avec la participation de Za'Saad

Sheet VENTES
A1: Objet | B1: Prix de vente | C1: Marge | D1: % de marge | E1: Materiel 1 | F1: Quantitée 1 | G1: Materiel 2 | H1: Quantitée 2 | I1: Materiel 3 | J1: Quantitée 3 | K1: Materiel 4 | L1: Quantitée 4 | M1: Materiel 5 | N1: Quantitée 5 | O1: Materiel 6 | P1: Quantitée 6 | Q1: Cout de création
A2: Bandages de pieds | B2: 20 | C2: =B2-Q2 -> 19.666667 | D2: =(C2/Q2) -> 59 | E2: Fil | F2: 1 | Q2: =SUM( IFERROR(VLOOKUP(E2,MATERIAUX!$A$1:$D$27,4,FALSE)*F2,0), IFERROR(VLOOKUP(G2,MATERIAUX!$A$1:$D$27,4,FALSE)*H2,0), IFERROR(VLOOKUP(I2,MATERIAUX!$A$1:$D$27,4,FALSE)*J2,0), IFERROR(VLOOKUP(K2,MATERIAUX!$A$1:$D$27,4,FALSE)*L2,0), IFERROR(VLOOKUP(M2,MATERIAUX!$A$1:$D$27,4,FALSE)*N2,0), IFERROR(VLOOKUP(O2,MATERIAUX!$A$1:$D$27,4,FALSE)*P2,0) ) -> 0.33333333
A3: Bottes | B3: 20 | C3: =B3-Q3 -> 16.666667 | D3: =(C3/Q3) -> 5 | E3: Fil | F3: 1 | G3: Cuir | H3: 1 | Q3: =SUM( IFERROR(VLOOKUP(E3,MATERIAUX!$A$1:$D$27,4,FALSE)*F3,0), IFERROR(VLOOKUP(G3,MATERIAUX!$A$1:$D$27,4,FALSE)*H3,0), IFERROR(VLOOKUP(I3,MATERIAUX!$A$1:$D$27,4,FALSE)*J3,0), IFERROR(VLOOKUP(K3,MATERIAUX!$A$1:$D$27,4,FALSE)*L3,0), IFERROR(VLOOKUP(M3,MATERIAUX!$A$1:$D$27,4,FALSE)*N3,0), IFERROR(VLOOKUP(O3,MATERIAUX!$A$1:$D$27,4,FALSE)*P3,0) ) -> 3.3333333
A4: Bottes | B4: 20 | C4: =B4-Q4 -> 13.333333 | D4: =(C4/Q4) -> 2 | E4: Fil | F4: 2 | G4: Cuir | H4: 2 | Q4: =SUM( IFERROR(VLOOKUP(E4,MATERIAUX!$A$1:$D$27,4,FALSE)*F4,0), IFERROR(VLOOKUP(G4,MATERIAUX!$A$1:$D$27,4,FALSE)*H4,0), IFERROR(VLOOKUP(I4,MATERIAUX!$A$1:$D$27,4,FALSE)*J4,0), IFERROR(VLOOKUP(K4,MATERIAUX!$A$1:$D$27,4,FALSE)*L4,0), IFERROR(VLOOKUP(M4,MATERIAUX!$A$1:$D$27,4,FALSE)*N4,0), IFERROR(VLOOKUP(O4,MATERIAUX!$A$1:$D$27,4,FALSE)*P4,0) ) -> 6.6666667
A5: Bottes | B5: 20 | C5: =B5-Q5 -> 13.666667 | D5: =(C5/Q5) -> 2.1578947 | E5: Fil | F5: 1 | G5: Cuir | H5: 2 | Q5: =SUM( IFERROR(VLOOKUP(E5,MATERIAUX!$A$1:$D$27,4,FALSE)*F5,0), IFERROR(VLOOKUP(G5,MATERIAUX!$A$1:$D$27,4,FALSE)*H5,0), IFERROR(VLOOKUP(I5,MATERIAUX!$A$1:$D$27,4,FALSE)*J5,0), IFERROR(VLOOKUP(K5,MATERIAUX!$A$1:$D$27,4,FALSE)*L5,0), IFERROR(VLOOKUP(M5,MATERIAUX!$A$1:$D$27,4,FALSE)*N5,0), IFERROR(VLOOKUP(O5,MATERIAUX!$A$1:$D$27,4,FALSE)*P5,0) ) -> 6.3333333
A6: Bottes raffinées | B6: 20 | C6: =B6-Q6 -> 13 | D6: =(C6/Q6) -> 1.8571429 | E6: Fil | F6: 3 | G6: Cuir | H6: 2 | Q6: =SUM( IFERROR(VLOOKUP(E6,MATERIAUX!$A$1:$D$27,4,FALSE)*F6,0), IFERROR(VLOOKUP(G6,MATERIAUX!$A$1:$D$27,4,FALSE)*H6,0), IFERROR(VLOOKUP(I6,MATERIAUX!$A$1:$D$27,4,FALSE)*J6,0), IFERROR(VLOOKUP(K6,MATERIAUX!$A$1:$D$27,4,FALSE)*L6,0), IFERROR(VLOOKUP(M6,MATERIAUX!$A$1:$D$27,4,FALSE)*N6,0), IFERROR(VLOOKUP(O6,MATERIAUX!$A$1:$D$27,4,FALSE)*P6,0) ) -> 7
A7: Chaussures | B7: 20 | C7: =B7-Q7 -> 16.666667 | D7: =(C7/Q7) -> 5 | E7: Fil | F7: 1 | G7: Cuir | H7: 1 | Q7: =SUM( IFERROR(VLOOKUP(E7,MATERIAUX!$A$1:$D$27,4,FALSE)*F7,0), IFERROR(VLOOKUP(G7,MATERIAUX!$A$1:$D$27,4,FALSE)*H7,0), IFERROR(VLOOKUP(I7,MATERIAUX!$A$1:$D$27,4,FALSE)*J7,0), IFERROR(VLOOKUP(K7,MATERIAUX!$A$1:$D$27,4,FALSE)*L7,0), IFERROR(VLOOKUP(M7,MATERIAUX!$A$1:$D$27,4,FALSE)*N7,0), IFERROR(VLOOKUP(O7,MATERIAUX!$A$1:$D$27,4,FALSE)*P7,0) ) -> 3.3333333
A8: Priest Sandals | B8: 20 | C8: =B8-Q8 -> 13.333333 | D8: =(C8/Q8) -> 2 | E8: Fil | F8: 2 | G8: Cuir | H8: 2 | Q8: =SUM( IFERROR(VLOOKUP(E8,MATERIAUX!$A$1:$D$27,4,FALSE)*F8,0), IFERROR(VLOOKUP(G8,MATERIAUX!$A$1:$D$27,4,FALSE)*H8,0), IFERROR(VLOOKUP(I8,MATERIAUX!$A$1:$D$27,4,FALSE)*J8,0), IFERROR(VLOOKUP(K8,MATERIAUX!$A$1:$D$27,4,FALSE)*L8,0), IFERROR(VLOOKUP(M8,MATERIAUX!$A$1:$D$27,4,FALSE)*N8,0), IFERROR(VLOOKUP(O8,MATERIAUX!$A$1:$D$27,4,FALSE)*P8,0) ) -> 6.6666667
A9: Common Clothes | B9: 30 | C9: =B9-Q9 -> 26.9 | D9: =(C9/Q9) -> 8.6774194 | E9: Cuir | F9: 1 | G9: Coton | H9: 1 | Q9: =SUM( IFERROR(VLOOKUP(E9,MATERIAUX!$A$1:$D$27,4,FALSE)*F9,0), IFERROR(VLOOKUP(G9,MATERIAUX!$A$1:$D$27,4,FALSE)*H9,0), IFERROR(VLOOKUP(I9,MATERIAUX!$A$1:$D$27,4,FALSE)*J9,0), IFERROR(VLOOKUP(K9,MATERIAUX!$A$1:$D$27,4,FALSE)*L9,0), IFERROR(VLOOKUP(M9,MATERIAUX!$A$1:$D$27,4,FALSE)*N9,0), IFERROR(VLOOKUP(O9,MATERIAUX!$A$1:$D$27,4,FALSE)*P9,0) ) -> 3.1
A10: Common robes | B10: 30 | C10: =B10-Q10 -> 23.5 | D10: =(C10/Q10) -> 3.6153846 | E10: Cuir | F10: 2 | G10: Coton | H10: 5 | Q10: =SUM( IFERROR(VLOOKUP(E10,MATERIAUX!$A$1:$D$27,4,FALSE)*F10,0), IFERROR(VLOOKUP(G10,MATERIAUX!$A$1:$D$27,4,FALSE)*H10,0), IFERROR(VLOOKUP(I10,MATERIAUX!$A$1:$D$27,4,FALSE)*J10,0), IFERROR(VLOOKUP(K10,MATERIAUX!$A$1:$D$27,4,FALSE)*L10,0), IFERROR(VLOOKUP(M10,MATERIAUX!$A$1:$D$27,4,FALSE)*N10,0), IFERROR(VLOOKUP(O10,MATERIAUX!$A$1:$D$27,4,FALSE)*P10,0) ) -> 6.5
A11: Fine Clothes | B11: 40 | C11: =B11-Q11 -> 35.333333 | D11: =(C11/Q11) -> 7.5714286 | E11: Cuir | F11: 1 | G11: Fil | H11: 5 | Q11: =SUM( IFERROR(VLOOKUP(E11,MATERIAUX!$A$1:$D$27,4,FALSE)*F11,0), IFERROR(VLOOKUP(G11,MATERIAUX!$A$1:$D$27,4,FALSE)*H11,0), IFERROR(VLOOKUP(I11,MATERIAUX!$A$1:$D$27,4,FALSE)*J11,0), IFERROR(VLOOKUP(K11,MATERIAUX!$A$1:$D$27,4,FALSE)*L11,0), IFERROR(VLOOKUP(M11,MATERIAUX!$A$1:$D$27,4,FALSE)*N11,0), IFERROR(VLOOKUP(O11,MATERIAUX!$A$1:$D$27,4,FALSE)*P11,0) ) -> 4.6666667
A12: Fine Clothes Arcana | B12: 100 | C12: =B12-Q12 -> 60.666667 | D12: =(C12/Q12) -> 1.5423729 | E12: Argent | F12: 2 | G12: Or | H12: 2 | I12: Cuir | J12: 2 | K12: Fil | L12: 16 | Q12: =SUM( IFERROR(VLOOKUP(E12,MATERIAUX!$A$1:$D$27,4,FALSE)*F12,0), IFERROR(VLOOKUP(G12,MATERIAUX!$A$1:$D$27,4,FALSE)*H12,0), IFERROR(VLOOKUP(I12,MATERIAUX!$A$1:$D$27,4,FALSE)*J12,0), IFERROR(VLOOKUP(K12,MATERIAUX!$A$1:$D$27,4,FALSE)*L12,0), IFERROR(VLOOKUP(M12,MATERIAUX!$A$1:$D$27,4,FALSE)*N12,0), IFERROR(VLOOKUP(O12,MATERIAUX!$A$1:$D$27,4,FALSE)*P12,0) ) -> 39.333333
A13: Fine Clothes Aureate Death | B13: 100 | C13: =B13-Q13 -> 60.666667 | D13: =(C13/Q13) -> 1.5423729 | E13: Argent | F13: 2 | G13: Or | H13: 2 | I13: Cuir | J13: 2 | K13: Fil | L13: 16 | Q13: =SUM( IFERROR(VLOOKUP(E13,MATERIAUX!$A$1:$D$27,4,FALSE)*F13,0), IFERROR(VLOOKUP(G13,MATERIAUX!$A$1:$D$27,4,FALSE)*H13,0), IFERROR(VLOOKUP(I13,MATERIAUX!$A$1:$D$27,4,FALSE)*J13,0), IFERROR(VLOOKUP(K13,MATERIAUX!$A$1:$D$27,4,FALSE)*L13,0), IFERROR(VLOOKUP(M13,MATERIAUX!$A$1:$D$27,4,FALSE)*N13,0), IFERROR(VLOOKUP(O13,MATERIAUX!$A$1:$D$27,4,FALSE)*P13,0) ) -> 39.333333
A14: Fine Clothes Bardic | B14: 100 | C14: =B14-Q14 -> 60.666667 | D14: =(C14/Q14) -> 1.5423729 | E14: Argent | F14: 2 | G14: Or | H14: 2 | I14: Cuir | J14: 2 | K14: Fil | L14: 16 | Q14: =SUM( IFERROR(VLOOKUP(E14,MATERIAUX!$A$1:$D$27,4,FALSE)*F14,0), IFERROR(VLOOKUP(G14,MATERIAUX!$A$1:$D$27,4,FALSE)*H14,0), IFERROR(VLOOKUP(I14,MATERIAUX!$A$1:$D$27,4,FALSE)*J14,0), IFERROR(VLOOKUP(K14,MATERIAUX!$A$1:$D$27,4,FALSE)*L14,0), IFERROR(VLOOKUP(M14,MATERIAUX!$A$1:$D$27,4,FALSE)*N14,0), IFERROR(VLOOKUP(O14,MATERIAUX!$A$1:$D$27,4,FALSE)*P14,0) ) -> 39.333333
A15: Fine Clothes Blood Moon | B15: 100 | C15: =B15-Q15 -> 60.666667 | D15: =(C15/Q15) -> 1.5423729 | E15: Argent | F15: 2 | G15: Or | H15: 2 | I15: Cuir | J15: 2 | K15: Fil | L15: 16 | Q15: =SUM( IFERROR(VLOOKUP(E15,MATERIAUX!$A$1:$D$27,4,FALSE)*F15,0), IFERROR(VLOOKUP(G15,MATERIAUX!$A$1:$D$27,4,FALSE)*H15,0), IFERROR(VLOOKUP(I15,MATERIAUX!$A$1:$D$27,4,FALSE)*J15,0), IFERROR(VLOOKUP(K15,MATERIAUX!$A$1:$D$27,4,FALSE)*L15,0), IFERROR(VLOOKUP(M15,MATERIAUX!$A$1:$D$27,4,FALSE)*N15,0), IFERROR(VLOOKUP(O15,MATERIAUX!$A$1:$D$27,4,FALSE)*P15,0) ) -> 39.333333
A16: Fine Clothes Blood Pact | B16: 100 | C16: =B16-Q16 -> 60.666667 | D16: =(C16/Q16) -> 1.5423729 | E16: Argent | F16: 2 | G16: Or | H16: 2 | I16: Cuir | J16: 2 | K16: Fil | L16: 16 | Q16: =SUM( IFERROR(VLOOKUP(E16,MATERIAUX!$A$1:$D$27,4,FALSE)*F16,0), IFERROR(VLOOKUP(G16,MATERIAUX!$A$1:$D$27,4,FALSE)*H16,0), IFERROR(VLOOKUP(I16,MATERIAUX!$A$1:$D$27,4,FALSE)*J16,0), IFERROR(VLOOKUP(K16,MATERIAUX!$A$1:$D$27,4,FALSE)*L16,0), IFERROR(VLOOKUP(M16,MATERIAUX!$A$1:$D$27,4,FALSE)*N16,0), IFERROR(VLOOKUP(O16,MATERIAUX!$A$1:$D$27,4,FALSE)*P16,0) ) -> 39.333333
A17: Fine Clothes Blue Moon | B17: 100 | C17: =B17-Q17 -> 60.666667 | D17: =(C17/Q17) -> 1.5423729 | E17: Argent | F17: 2 | G17: Or | H17: 2 | I17: Cuir | J17: 2 | K17: Fil | L17: 16 | Q17: =SUM( IFERROR(VLOOKUP(E17,MATERIAUX!$A$1:$D$27,4,FALSE)*F17,0), IFERROR(VLOOKUP(G17,MATERIAUX!$A$1:$D$27,4,FALSE)*H17,0), IFERROR(VLOOKUP(I17,MATERIAUX!$A$1:$D$27,4,FALSE)*J17,0), IFERROR(VLOOKUP(K17,MATERIAUX!$A$1:$D$27,4,FALSE)*L17,0), IFERROR(VLOOKUP(M17,MATERIAUX!$A$1:$D$27,4,FALSE)*N17,0), IFERROR(VLOOKUP(O17,MATERIAUX!$A$1:$D$27,4,FALSE)*P17,0) ) -> 39.333333
A18: Fine Clothes Burnished | B18: 100 | C18: =B18-Q18 -> 60.666667 | D18: =(C18/Q18) -> 1.5423729 | E18: Argent | F18: 2 | G18: Or | H18: 2 | I18: Cuir | J18: 2 | K18: Fil | L18: 16 | Q18: =SUM( IFERROR(VLOOKUP(E18,MATERIAUX!$A$1:$D$27,4,FALSE)*F18,0), IFERROR(VLOOKUP(G18,MATERIAUX!$A$1:$D$27,4,FALSE)*H18,0), IFERROR(VLOOKUP(I18,MATERIAUX!$A$1:$D$27,4,FALSE)*J18,0), IFERROR(VLOOKUP(K18,MATERIAUX!$A$1:$D$27,4,FALSE)*L18,0), IFERROR(VLOOKUP(M18,MATERIAUX!$A$1:$D$27,4,FALSE)*N18,0), IFERROR(VLOOKUP(O18,MATERIAUX!$A$1:$D$27,4,FALSE)*P18,0) ) -> 39.333333
A19: Fine Clothes Charcoal | B19: 100 | C19: =B19-Q19 -> 60.666667 | D19: =(C19/Q19) -> 1.5423729 | E19: Argent | F19: 2 | G19: Or | H19: 2 | I19: Cuir | J19: 2 | K19: Fil | L19: 16 | Q19: =SUM( IFERROR(VLOOKUP(E19,MATERIAUX!$A$1:$D$27,4,FALSE)*F19,0), IFERROR(VLOOKUP(G19,MATERIAUX!$A$1:$D$27,4,FALSE)*H19,0), IFERROR(VLOOKUP(I19,MATERIAUX!$A$1:$D$27,4,FALSE)*J19,0), IFERROR(VLOOKUP(K19,MATERIAUX!$A$1:$D$27,4,FALSE)*L19,0), IFERROR(VLOOKUP(M19,MATERIAUX!$A$1:$D$27,4,FALSE)*N19,0), IFERROR(VLOOKUP(O19,MATERIAUX!$A$1:$D$27,4,FALSE)*P19,0) ) -> 39.333333
A20: Fine Clothes Darkmoon | B20: 100 | C20: =B20-Q20 -> 60.666667 | D20: =(C20/Q20) -> 1.5423729 | E20: Argent | F20: 2 | G20: Or | H20: 2 | I20: Cuir | J20: 2 | K20: Fil | L20: 16 | Q20: =SUM( IFERROR(VLOOKUP(E20,MATERIAUX!$A$1:$D$27,4,FALSE)*F20,0), IFERROR(VLOOKUP(G20,MATERIAUX!$A$1:$D$27,4,FALSE)*H20,0), IFERROR(VLOOKUP(I20,MATERIAUX!$A$1:$D$27,4,FALSE)*J20,0), IFERROR(VLOOKUP(K20,MATERIAUX!$A$1:$D$27,4,FALSE)*L20,0), IFERROR(VLOOKUP(M20,MATERIAUX!$A$1:$D$27,4,FALSE)*N20,0), IFERROR(VLOOKUP(O20,MATERIAUX!$A$1:$D$27,4,FALSE)*P20,0) ) -> 39.333333
A21: Fine Clothes Deepwood | B21: 100 | C21: =B21-Q21 -> 60.666667 | D21: =(C21/Q21) -> 1.5423729 | E21: Argent | F21: 2 | G21: Or | H21: 2 | I21: Cuir | J21: 2 | K21: Fil | L21: 16 | Q21: =SUM( IFERROR(VLOOKUP(E21,MATERIAUX!$A$1:$D$27,4,FALSE)*F21,0), IFERROR(VLOOKUP(G21,MATERIAUX!$A$1:$D$27,4,FALSE)*H21,0), IFERROR(VLOOKUP(I21,MATERIAUX!$A$1:$D$27,4,FALSE)*J21,0), IFERROR(VLOOKUP(K21,MATERIAUX!$A$1:$D$27,4,FALSE)*L21,0), IFERROR(VLOOKUP(M21,MATERIAUX!$A$1:$D$27,4,FALSE)*N21,0), IFERROR(VLOOKUP(O21,MATERIAUX!$A$1:$D$27,4,FALSE)*P21,0) ) -> 39.333333
A22: Fine Clothes Fuscia | B22: 100 | C22: =B22-Q22 -> 60.666667 | D22: =(C22/Q22) -> 1.5423729 | E22: Argent | F22: 2 | G22: Or | H22: 2 | I22: Cuir | J22: 2 | K22: Fil | L22: 16 | Q22: =SUM( IFERROR(VLOOKUP(E22,MATERIAUX!$A$1:$D$27,4,FALSE)*F22,0), IFERROR(VLOOKUP(G22,MATERIAUX!$A$1:$D$27,4,FALSE)*H22,0), IFERROR(VLOOKUP(I22,MATERIAUX!$A$1:$D$27,4,FALSE)*J22,0), IFERROR(VLOOKUP(K22,MATERIAUX!$A$1:$D$27,4,FALSE)*L22,0), IFERROR(VLOOKUP(M22,MATERIAUX!$A$1:$D$27,4,FALSE)*N22,0), IFERROR(VLOOKUP(O22,MATERIAUX!$A$1:$D$27,4,FALSE)*P22,0) ) -> 39.333333
A23: Fine Clothes Ilinalta | B23: 100 | C23: =B23-Q23 -> 60.666667 | D23: =(C23/Q23) -> 1.5423729 | E23: Argent | F23: 2 | G23: Or | H23: 2 | I23: Cuir | J23: 2 | K23: Fil | L23: 16 | Q23: =SUM( IFERROR(VLOOKUP(E23,MATERIAUX!$A$1:$D$27,4,FALSE)*F23,0), IFERROR(VLOOKUP(G23,MATERIAUX!$A$1:$D$27,4,FALSE)*H23,0), IFERROR(VLOOKUP(I23,MATERIAUX!$A$1:$D$27,4,FALSE)*J23,0), IFERROR(VLOOKUP(K23,MATERIAUX!$A$1:$D$27,4,FALSE)*L23,0), IFERROR(VLOOKUP(M23,MATERIAUX!$A$1:$D$27,4,FALSE)*N23,0), IFERROR(VLOOKUP(O23,MATERIAUX!$A$1:$D$27,4,FALSE)*P23,0) ) -> 39.333333
... A30: Fine Clothes Wolfsbane | B30: 100 | C30: =B30-Q30 -> 60.666667 | D30: =(C30/Q30) -> 1.5423729 | E30: Argent | F30: 2 | G30: Or | H30: 2 | I30: Cuir | J30: 2 | K30: Fil | L30: 16 | Q30: =SUM( IFERROR(VLOOKUP(E30,MATERIAUX!$A$1:$D$27,4,FALSE)*F30,0), IFERROR(VLOOKUP(G30,MATERIAUX!$A$1:$D$27,4,FALSE)*H30,0), IFERROR(VLOOKUP(I30,MATERIAUX!$A$1:$D$27,4,FALSE)*J30,0), IFERROR(VLOOKUP(K30,MATERIAUX!$A$1:$D$27,4,FALSE)*L30,0), IFERROR(VLOOKUP(M30,MATERIAUX!$A$1:$D$27,4,FALSE)*N30,0), IFERROR(VLOOKUP(O30,MATERIAUX!$A$1:$D$27,4,FALSE)*P30,0) ) -> 39.333333
A31: Habit de taverne | B31: 20 | C31: =B31-Q31 -> 18.666667 | D31: =(C31/Q31) -> 14 | E31: Fil | F31: 4 | Q31: =SUM( IFERROR(VLOOKUP(E31,MATERIAUX!$A$1:$D$27,4,FALSE)*F31,0), IFERROR(VLOOKUP(G31,MATERIAUX!$A$1:$D$27,4,FALSE)*H31,0), IFERROR(VLOOKUP(I31,MATERIAUX!$A$1:$D$27,4,FALSE)*J31,0), IFERROR(VLOOKUP(K31,MATERIAUX!$A$1:$D$27,4,FALSE)*L31,0), IFERROR(VLOOKUP(M31,MATERIAUX!$A$1:$D$27,4,FALSE)*N31,0), IFERROR(VLOOKUP(O31,MATERIAUX!$A$1:$D$27,4,FALSE)*P31,0) ) -> 1.3333333
A32: Heavy Quilted Surcoat 01 | B32: 40 | C32: =B32-Q32 -> 32.8 | D32: =(C32/Q32) -> 4.5555556 | E32: Cuir | F32: 2 | G32: Coton | H32: 12 | Q32: =SUM( IFERROR(VLOOKUP(E32,MATERIAUX!$A$1:$D$27,4,FALSE)*F32,0), IFERROR(VLOOKUP(G32,MATERIAUX!$A$1:$D$27,4,FALSE)*H32,0), IFERROR(VLOOKUP(I32,MATERIAUX!$A$1:$D$27,4,FALSE)*J32,0), IFERROR(VLOOKUP(K32,MATERIAUX!$A$1:$D$27,4,FALSE)*L32,0), IFERROR(VLOOKUP(M32,MATERIAUX!$A$1:$D$27,4,FALSE)*N32,0), IFERROR(VLOOKUP(O32,MATERIAUX!$A$1:$D$27,4,FALSE)*P32,0) ) -> 7.2
A33: Hooded Monk Tunic | B33: 20 | C33: =B33-Q33 -> 18.666667 | D33: =(C33/Q33) -> 14 | E33: Fil | F33: 4 | Q33: =SUM( IFERROR(VLOOKUP(E33,MATERIAUX!$A$1:$D$27,4,FALSE)*F33,0), IFERROR(VLOOKUP(G33,MATERIAUX!$A$1:$D$27,4,FALSE)*H33,0), IFERROR(VLOOKUP(I33,MATERIAUX!$A$1:$D$27,4,FALSE)*J33,0), IFERROR(VLOOKUP(K33,MATERIAUX!$A$1:$D$27,4,FALSE)*L33,0), IFERROR(VLOOKUP(M33,MATERIAUX!$A$1:$D$27,4,FALSE)*N33,0), IFERROR(VLOOKUP(O33,MATERIAUX!$A$1:$D$27,4,FALSE)*P33,0) ) -> 1.3333333
A34: Hooded Necromancer Robes | B34: 20 | C34: =B34-Q34 -> 18.666667 | D34: =(C34/Q34) -> 14 | E34: Fil | F34: 4 | Q34: =SUM( IFERROR(VLOOKUP(E34,MATERIAUX!$A$1:$D$27,4,FALSE)*F34,0), IFERROR(VLOOKUP(G34,MATERIAUX!$A$1:$D$27,4,FALSE)*H34,0), IFERROR(VLOOKUP(I34,MATERIAUX!$A$1:$D$27,4,FALSE)*J34,0), IFERROR(VLOOKUP(K34,MATERIAUX!$A$1:$D$27,4,FALSE)*L34,0), IFERROR(VLOOKUP(M34,MATERIAUX!$A$1:$D$27,4,FALSE)*N34,0), IFERROR(VLOOKUP(O34,MATERIAUX!$A$1:$D$27,4,FALSE)*P34,0) ) -> 1.3333333
A35: Monk Tunic | B35: 20 | C35: =B35-Q35 -> 18.666667 | D35: =(C35/Q35) -> 14 | E35: Fil | F35: 4 | Q35: =SUM( IFERROR(VLOOKUP(E35,MATERIAUX!$A$1:$D$27,4,FALSE)*F35,0), IFERROR(VLOOKUP(G35,MATERIAUX!$A$1:$D$27,4,FALSE)*H35,0), IFERROR(VLOOKUP(I35,MATERIAUX!$A$1:$D$27,4,FALSE)*J35,0), IFERROR(VLOOKUP(K35,MATERIAUX!$A$1:$D$27,4,FALSE)*L35,0), IFERROR(VLOOKUP(M35,MATERIAUX!$A$1:$D$27,4,FALSE)*N35,0), IFERROR(VLOOKUP(O35,MATERIAUX!$A$1:$D$27,4,FALSE)*P35,0) ) -> 1.3333333
A36: Necormancer Robes | B36: 20 | C36: =B36-Q36 -> 18.666667 | D36: =(C36/Q36) -> 14 | E36: Fil | F36: 4 | Q36: =SUM( IFERROR(VLOOKUP(E36,MATERIAUX!$A$1:$D$27,4,FALSE)*F36,0), IFERROR(VLOOKUP(G36,MATERIAUX!$A$1:$D$27,4,FALSE)*H36,0), IFERROR(VLOOKUP(I36,MATERIAUX!$A$1:$D$27,4,FALSE)*J36,0), IFERROR(VLOOKUP(K36,MATERIAUX!$A$1:$D$27,4,FALSE)*L36,0), IFERROR(VLOOKUP(M36,MATERIAUX!$A$1:$D$27,4,FALSE)*N36,0), IFERROR(VLOOKUP(O36,MATERIAUX!$A$1:$D$27,4,FALSE)*P36,0) ) -> 1.3333333
A37: Pantalon usé | B37: 10 | C37: =B37-Q37 -> 9.6666667 | D37: =(C37/Q37) -> 29 | E37: Fil | F37: 1 | Q37: =SUM( IFERROR(VLOOKUP(E37,MATERIAUX!$A$1:$D$27,4,FALSE)*F37,0), IFERROR(VLOOKUP(G37,MATERIAUX!$A$1:$D$27,4,FALSE)*H37,0), IFERROR(VLOOKUP(I37,MATERIAUX!$A$1:$D$27,4,FALSE)*J37,0), IFERROR(VLOOKUP(K37,MATERIAUX!$A$1:$D$27,4,FALSE)*L37,0), IFERROR(VLOOKUP(M37,MATERIAUX!$A$1:$D$27,4,FALSE)*N37,0), IFERROR(VLOOKUP(O37,MATERIAUX!$A$1:$D$27,4,FALSE)*P37,0) ) -> 0.33333333
A38: Quilted Surcoat 01 | B38: 40 | C38: =B38-Q38 -> 32.8 | D38: =(C38/Q38) -> 4.5555556 | E38: Coton | F38: 12 | G38: Cuir | H38: 2 | Q38: =SUM( IFERROR(VLOOKUP(E38,MATERIAUX!$A$1:$D$27,4,FALSE)*F38,0), IFERROR(VLOOKUP(G38,MATERIAUX!$A$1:$D$27,4,FALSE)*H38,0), IFERROR(VLOOKUP(I38,MATERIAUX!$A$1:$D$27,4,FALSE)*J38,0), IFERROR(VLOOKUP(K38,MATERIAUX!$A$1:$D$27,4,FALSE)*L38,0), IFERROR(VLOOKUP(M38,MATERIAUX!$A$1:$D$27,4,FALSE)*N38,0), IFERROR(VLOOKUP(O38,MATERIAUX!$A$1:$D$27,4,FALSE)*P38,0) ) -> 7.2
A39: Quilted Surcoat 02 | B39: 40 | C39: =B39-Q39 -> 32.8 | D39: =(C39/Q39) -> 4.5555556 | E39: Coton | F39: 12 | G39: Cuir | H39: 2 | Q39: =SUM( IFERROR(VLOOKUP(E39,MATERIAUX!$A$1:$D$27,4,FALSE)*F39,0), IFERROR(VLOOKUP(G39,MATERIAUX!$A$1:$D$27,4,FALSE)*H39,0), IFERROR(VLOOKUP(I39,MATERIAUX!$A$1:$D$27,4,FALSE)*J39,0), IFERROR(VLOOKUP(K39,MATERIAUX!$A$1:$D$27,4,FALSE)*L39,0), IFERROR(VLOOKUP(M39,MATERIAUX!$A$1:$D$27,4,FALSE)*N39,0), IFERROR(VLOOKUP(O39,MATERIAUX!$A$1:$D$27,4,FALSE)*P39,0) ) -> 7.2
A40: Quilted Tunic | B40: 40 | C40: =B40-Q40 -> 32.8 | D40: =(C40/Q40) -> 4.5555556 | E40: Coton | F40: 12 | G40: Cuir | H40: 2 | Q40: =SUM( IFERROR(VLOOKUP(E40,MATERIAUX!$A$1:$D$27,4,FALSE)*F40,0), IFERROR(VLOOKUP(G40,MATERIAUX!$A$1:$D$27,4,FALSE)*H40,0), IFERROR(VLOOKUP(I40,MATERIAUX!$A$1:$D$27,4,FALSE)*J40,0), IFERROR(VLOOKUP(K40,MATERIAUX!$A$1:$D$27,4,FALSE)*L40,0), IFERROR(VLOOKUP(M40,MATERIAUX!$A$1:$D$27,4,FALSE)*N40,0), IFERROR(VLOOKUP(O40,MATERIAUX!$A$1:$D$27,4,FALSE)*P40,0) ) -> 7.2
A41: Quilted Tunic and Green Robes | B41: 40 | C41: =B41-Q41 -> 32.8 | D41: =(C41/Q41) -> 4.5555556 | E41: Coton | F41: 12 | G41: Cuir | H41: 2 | Q41: =SUM( IFERROR(VLOOKUP(E41,MATERIAUX!$A$1:$D$27,4,FALSE)*F41,0), IFERROR(VLOOKUP(G41,MATERIAUX!$A$1:$D$27,4,FALSE)*H41,0), IFERROR(VLOOKUP(I41,MATERIAUX!$A$1:$D$27,4,FALSE)*J41,0), IFERROR(VLOOKUP(K41,MATERIAUX!$A$1:$D$27,4,FALSE)*L41,0), IFERROR(VLOOKUP(M41,MATERIAUX!$A$1:$D$27,4,FALSE)*N41,0), IFERROR(VLOOKUP(O41,MATERIAUX!$A$1:$D$27,4,FALSE)*P41,0) ) -> 7.2
A42: Quilted Tunic and White Robes | B42: 40 | C42: =B42-Q42 -> 32.8 | D42: =(C42/Q42) -> 4.5555556 | E42: Coton | F42: 12 | G42: Cuir | H42: 2 | Q42: =SUM( IFERROR(VLOOKUP(E42,MATERIAUX!$A$1:$D$27,4,FALSE)*F42,0), IFERROR(VLOOKUP(G42,MATERIAUX!$A$1:$D$27,4,FALSE)*H42,0), IFERROR(VLOOKUP(I42,MATERIAUX!$A$1:$D$27,4,FALSE)*J42,0), IFERROR(VLOOKUP(K42,MATERIAUX!$A$1:$D$27,4,FALSE)*L42,0), IFERROR(VLOOKUP(M42,MATERIAUX!$A$1:$D$27,4,FALSE)*N42,0), IFERROR(VLOOKUP(O42,MATERIAUX!$A$1:$D$27,4,FALSE)*P42,0) ) -> 7.2
A43: Quilted Tunic with Surcoat | B43: 40 | C43: =B43-Q43 -> 32.8 | D43: =(C43/Q43) -> 4.5555556 | E43: Coton | F43: 12 | G43: Cuir | H43: 2 | Q43: =SUM( IFERROR(VLOOKUP(E43,MATERIAUX!$A$1:$D$27,4,FALSE)*F43,0), IFERROR(VLOOKUP(G43,MATERIAUX!$A$1:$D$27,4,FALSE)*H43,0), IFERROR(VLOOKUP(I43,MATERIAUX!$A$1:$D$27,4,FALSE)*J43,0), IFERROR(VLOOKUP(K43,MATERIAUX!$A$1:$D$27,4,FALSE)*L43,0), IFERROR(VLOOKUP(M43,MATERIAUX!$A$1:$D$27,4,FALSE)*N43,0), IFERROR(VLOOKUP(O43,MATERIAUX!$A$1:$D$27,4,FALSE)*P43,0) ) -> 7.2
A44: Robe (Bleu, Moine, Grise, Marron, Noire, Rouge, Verte, usée) | B44: 20 | C44: =B44-Q44 -> 18.666667 | D44: =(C44/Q44) -> 14 | E44: Fil | F44: 4 | Q44: =SUM( IFERROR(VLOOKUP(E44,MATERIAUX!$A$1:$D$27,4,FALSE)*F44,0), IFERROR(VLOOKUP(G44,MATERIAUX!$A$1:$D$27,4,FALSE)*H44,0), IFERROR(VLOOKUP(I44,MATERIAUX!$A$1:$D$27,4,FALSE)*J44,0), IFERROR(VLOOKUP(K44,MATERIAUX!$A$1:$D$27,4,FALSE)*L44,0), IFERROR(VLOOKUP(M44,MATERIAUX!$A$1:$D$27,4,FALSE)*N44,0), IFERROR(VLOOKUP(O44,MATERIAUX!$A$1:$D$27,4,FALSE)*P44,0) ) -> 1.3333333
A45: Robe à Capuchon (Bleu, Moine, Grise, Marron, Noire, Rouge, Verte, usée) | B45: 20 | C45: =B45-Q45 -> 18.666667 | D45: =(C45/Q45) -> 14 | E45: Fil | F45: 4 | Q45: =SUM( IFERROR(VLOOKUP(E45,MATERIAUX!$A$1:$D$27,4,FALSE)*F45,0), IFERROR(VLOOKUP(G45,MATERIAUX!$A$1:$D$27,4,FALSE)*H45,0), IFERROR(VLOOKUP(I45,MATERIAUX!$A$1:$D$27,4,FALSE)*J45,0), IFERROR(VLOOKUP(K45,MATERIAUX!$A$1:$D$27,4,FALSE)*L45,0), IFERROR(VLOOKUP(M45,MATERIAUX!$A$1:$D$27,4,FALSE)*N45,0), IFERROR(VLOOKUP(O45,MATERIAUX!$A$1:$D$27,4,FALSE)*P45,0) ) -> 1.3333333
A46: Tablier de Forgeron | B46: 20 | C46: =B46-Q46 -> 16 | D46: =(C46/Q46) -> 4 | E46: Fil | F46: 3 | G46: Cuir | H46: 1 | Q46: =SUM( IFERROR(VLOOKUP(E46,MATERIAUX!$A$1:$D$27,4,FALSE)*F46,0), IFERROR(VLOOKUP(G46,MATERIAUX!$A$1:$D$27,4,FALSE)*H46,0), IFERROR(VLOOKUP(I46,MATERIAUX!$A$1:$D$27,4,FALSE)*J46,0), IFERROR(VLOOKUP(K46,MATERIAUX!$A$1:$D$27,4,FALSE)*L46,0), IFERROR(VLOOKUP(M46,MATERIAUX!$A$1:$D$27,4,FALSE)*N46,0), IFERROR(VLOOKUP(O46,MATERIAUX!$A$1:$D$27,4,FALSE)*P46,0) ) -> 4
A47: Traveller Robes (Noir, Marron, Gris, Rouge, Tan) | B47: 40 | C47: =B47-Q47 -> 37.25 | D47: =(C47/Q47) -> 13.545455 | E47: Coton | F47: 5 | G47: Bandes de cuir | H47: 3 | Q47: =SUM( IFERROR(VLOOKUP(E47,MATERIAUX!$A$1:$D$27,4,FALSE)*F47,0), IFERROR(VLOOKUP(G47,MATERIAUX!$A$1:$D$27,4,FALSE)*H47,0), IFERROR(VLOOKUP(I47,MATERIAUX!$A$1:$D$27,4,FALSE)*J47,0), IFERROR(VLOOKUP(K47,MATERIAUX!$A$1:$D$27,4,FALSE)*L47,0), IFERROR(VLOOKUP(M47,MATERIAUX!$A$1:$D$27,4,FALSE)*N47,0), IFERROR(VLOOKUP(O47,MATERIAUX!$A$1:$D$27,4,FALSE)*P47,0) ) -> 2.75
A48: Traveller Robes Hooded (Noir, Marron, Gris, Rouge, Tan) | B48: 40 | C48: =B48-Q48 -> 37.25 | D48: =(C48/Q48) -> 13.545455 | E48: Coton | F48: 5 | G48: Bandes de cuir | H48: 3 | Q48: =SUM( IFERROR(VLOOKUP(E48,MATERIAUX!$A$1:$D$27,4,FALSE)*F48,0), IFERROR(VLOOKUP(G48,MATERIAUX!$A$1:$D$27,4,FALSE)*H48,0), IFERROR(VLOOKUP(I48,MATERIAUX!$A$1:$D$27,4,FALSE)*J48,0), IFERROR(VLOOKUP(K48,MATERIAUX!$A$1:$D$27,4,FALSE)*L48,0), IFERROR(VLOOKUP(M48,MATERIAUX!$A$1:$D$27,4,FALSE)*N48,0), IFERROR(VLOOKUP(O48,MATERIAUX!$A$1:$D$27,4,FALSE)*P48,0) ) -> 2.75
A49: Tunique avec ceinture | B49: 20 | C49: =B49-Q49 -> 18.666667 | D49: =(C49/Q49) -> 14 | E49: Fil | F49: 4 | Q49: =SUM( IFERROR(VLOOKUP(E49,MATERIAUX!$A$1:$D$27,4,FALSE)*F49,0), IFERROR(VLOOKUP(G49,MATERIAUX!$A$1:$D$27,4,FALSE)*H49,0), IFERROR(VLOOKUP(I49,MATERIAUX!$A$1:$D$27,4,FALSE)*J49,0), IFERROR(VLOOKUP(K49,MATERIAUX!$A$1:$D$27,4,FALSE)*L49,0), IFERROR(VLOOKUP(M49,MATERIAUX!$A$1:$D$27,4,FALSE)*N49,0), IFERROR(VLOOKUP(O49,MATERIAUX!$A$1:$D$27,4,FALSE)*P49,0) ) -> 1.3333333
A50: Tunique de cuisinier | B50: 20 | C50: =B50-Q50 -> 18.666667 | D50: =(C50/Q50) -> 14 | E50: Fil | F50: 4 | Q50: =SUM( IFERROR(VLOOKUP(E50,MATERIAUX!$A$1:$D$27,4,FALSE)*F50,0), IFERROR(VLOOKUP(G50,MATERIAUX!$A$1:$D$27,4,FALSE)*H50,0), IFERROR(VLOOKUP(I50,MATERIAUX!$A$1:$D$27,4,FALSE)*J50,0), IFERROR(VLOOKUP(K50,MATERIAUX!$A$1:$D$27,4,FALSE)*L50,0), IFERROR(VLOOKUP(M50,MATERIAUX!$A$1:$D$27,4,FALSE)*N50,0), IFERROR(VLOOKUP(O50,MATERIAUX!$A$1:$D$27,4,FALSE)*P50,0) ) -> 1.3333333
A51: Tunique de jute | B51: 20 | C51: =B51-Q51 -> 19.666667 | D51: =(C51/Q51) -> 59 | E51: Fil | F51: 1 | Q51: =SUM( IFERROR(VLOOKUP(E51,MATERIAUX!$A$1:$D$27,4,FALSE)*F51,0), IFERROR(VLOOKUP(G51,MATERIAUX!$A$1:$D$27,4,FALSE)*H51,0), IFERROR(VLOOKUP(I51,MATERIAUX!$A$1:$D$27,4,FALSE)*J51,0), IFERROR(VLOOKUP(K51,MATERIAUX!$A$1:$D$27,4,FALSE)*L51,0), IFERROR(VLOOKUP(M51,MATERIAUX!$A$1:$D$27,4,FALSE)*N51,0), IFERROR(VLOOKUP(O51,MATERIAUX!$A$1:$D$27,4,FALSE)*P51,0) ) -> 0.33333333
A52: Vêtements | B52: 20 | C52: =B52-Q52 -> 18.666667 | D52: =(C52/Q52) -> 14 | E52: Fil | F52: 4 | Q52: =SUM( IFERROR(VLOOKUP(E52,MATERIAUX!$A$1:$D$27,4,FALSE)*F52,0), IFERROR(VLOOKUP(G52,MATERIAUX!$A$1:$D$27,4,FALSE)*H52,0), IFERROR(VLOOKUP(I52,MATERIAUX!$A$1:$D$27,4,FALSE)*J52,0), IFERROR(VLOOKUP(K52,MATERIAUX!$A$1:$D$27,4,FALSE)*L52,0), IFERROR(VLOOKUP(M52,MATERIAUX!$A$1:$D$27,4,FALSE)*N52,0), IFERROR(VLOOKUP(O52,MATERIAUX!$A$1:$D$27,4,FALSE)*P52,0) ) -> 1.3333333
A53: Vêtements (Léger colorés similaire tavernier) | B53: 20 | C53: =B53-Q53 -> 15.666667 | D53: =(C53/Q53) -> 3.6153846 | E53: Fil | F53: 4 | G53: Cuir | H53: 1 | K53: < | Q53: =SUM( IFERROR(VLOOKUP(E53,MATERIAUX!$A$1:$D$27,4,FALSE)*F53,0), IFERROR(VLOOKUP(G53,MATERIAUX!$A$1:$D$27,4,FALSE)*H53,0), IFERROR(VLOOKUP(I53,MATERIAUX!$A$1:$D$27,4,FALSE)*J53,0), IFERROR(VLOOKUP(K53,MATERIAUX!$A$1:$D$27,4,FALSE)*L53,0), IFERROR(VLOOKUP(M53,MATERIAUX!$A$1:$D$27,4,FALSE)*N53,0), IFERROR(VLOOKUP(O53,MATERIAUX!$A$1:$D$27,4,FALSE)*P53,0) ) -> 4.3333333
A54: Vêtements raffinés | B54: 40 | C54: =B54-Q54 -> 35.333333 | D54: =(C54/Q54) -> 7.5714286 | E54: Fil | F54: 5 | G54: Cuir | H54: 1 | Q54: =SUM( IFERROR(VLOOKUP(E54,MATERIAUX!$A$1:$D$27,4,FALSE)*F54,0), IFERROR(VLOOKUP(G54,MATERIAUX!$A$1:$D$27,4,FALSE)*H54,0), IFERROR(VLOOKUP(I54,MATERIAUX!$A$1:$D$27,4,FALSE)*J54,0), IFERROR(VLOOKUP(K54,MATERIAUX!$A$1:$D$27,4,FALSE)*L54,0), IFERROR(VLOOKUP(M54,MATERIAUX!$A$1:$D$27,4,FALSE)*N54,0), IFERROR(VLOOKUP(O54,MATERIAUX!$A$1:$D$27,4,FALSE)*P54,0) ) -> 4.6666667
A55: Cowl (Noir, Bleu, Marron, Vert, Gris, Monk, Rouge, Necromancer) | B55: 20 | C55: =B55-Q55 -> 19.333333 | D55: =(C55/Q55) -> 29 | E55: Fil | F55: 2 | Q55: =SUM( IFERROR(VLOOKUP(E55,MATERIAUX!$A$1:$D$27,4,FALSE)*F55,0), IFERROR(VLOOKUP(G55,MATERIAUX!$A$1:$D$27,4,FALSE)*H55,0), IFERROR(VLOOKUP(I55,MATERIAUX!$A$1:$D$27,4,FALSE)*J55,0), IFERROR(VLOOKUP(K55,MATERIAUX!$A$1:$D$27,4,FALSE)*L55,0), IFERROR(VLOOKUP(M55,MATERIAUX!$A$1:$D$27,4,FALSE)*N55,0), IFERROR(VLOOKUP(O55,MATERIAUX!$A$1:$D$27,4,FALSE)*P55,0) ) -> 0.66666667
A56: Bonnet usé | B56: 10 | C56: =B56-Q56 -> 9.6666667 | D56: =(C56/Q56) -> 29 | E56: Fil | F56: 1 | Q56: =SUM( IFERROR(VLOOKUP(E56,MATERIAUX!$A$1:$D$27,4,FALSE)*F56,0), IFERROR(VLOOKUP(G56,MATERIAUX!$A$1:$D$27,4,FALSE)*H56,0), IFERROR(VLOOKUP(I56,MATERIAUX!$A$1:$D$27,4,FALSE)*J56,0), IFERROR(VLOOKUP(K56,MATERIAUX!$A$1:$D$27,4,FALSE)*L56,0), IFERROR(VLOOKUP(M56,MATERIAUX!$A$1:$D$27,4,FALSE)*N56,0), IFERROR(VLOOKUP(O56,MATERIAUX!$A$1:$D$27,4,FALSE)*P56,0) ) -> 0.33333333
A57: Capuche | B57: 10 | C57: =B57-Q57 -> 9.3333333 | D57: =(C57/Q57) -> 14 | E57: Fil | F57: 2 | Q57: =SUM( IFERROR(VLOOKUP(E57,MATERIAUX!$A$1:$D$27,4,FALSE)*F57,0), IFERROR(VLOOKUP(G57,MATERIAUX!$A$1:$D$27,4,FALSE)*H57,0), IFERROR(VLOOKUP(I57,MATERIAUX!$A$1:$D$27,4,FALSE)*J57,0), IFERROR(VLOOKUP(K57,MATERIAUX!$A$1:$D$27,4,FALSE)*L57,0), IFERROR(VLOOKUP(M57,MATERIAUX!$A$1:$D$27,4,FALSE)*N57,0), IFERROR(VLOOKUP(O57,MATERIAUX!$A$1:$D$27,4,FALSE)*P57,0) ) -> 0.66666667
A58: Chapeau | B58: 20 | C58: =B58-Q58 -> 19.333333 | D58: =(C58/Q58) -> 29 | E58: Fil | F58: 2 | Q58: =SUM( IFERROR(VLOOKUP(E58,MATERIAUX!$A$1:$D$27,4,FALSE)*F58,0), IFERROR(VLOOKUP(G58,MATERIAUX!$A$1:$D$27,4,FALSE)*H58,0), IFERROR(VLOOKUP(I58,MATERIAUX!$A$1:$D$27,4,FALSE)*J58,0), IFERROR(VLOOKUP(K58,MATERIAUX!$A$1:$D$27,4,FALSE)*L58,0), IFERROR(VLOOKUP(M58,MATERIAUX!$A$1:$D$27,4,FALSE)*N58,0), IFERROR(VLOOKUP(O58,MATERIAUX!$A$1:$D$27,4,FALSE)*P58,0) ) -> 0.66666667
A59: Chapeau de deuil | B59: 20 | C59: =B59-Q59 -> 19.333333 | D59: =(C59/Q59) -> 29 | E59: Fil | F59: 2 | Q59: =SUM( IFERROR(VLOOKUP(E59,MATERIAUX!$A$1:$D$27,4,FALSE)*F59,0), IFERROR(VLOOKUP(G59,MATERIAUX!$A$1:$D$27,4,FALSE)*H59,0), IFERROR(VLOOKUP(I59,MATERIAUX!$A$1:$D$27,4,FALSE)*J59,0), IFERROR(VLOOKUP(K59,MATERIAUX!$A$1:$D$27,4,FALSE)*L59,0), IFERROR(VLOOKUP(M59,MATERIAUX!$A$1:$D$27,4,FALSE)*N59,0), IFERROR(VLOOKUP(O59,MATERIAUX!$A$1:$D$27,4,FALSE)*P59,0) ) -> 0.66666667
A60: Chapeau raffiné | B60: 20 | C60: =B60-Q60 -> 18.666667 | D60: =(C60/Q60) -> 14 | E60: Fil | F60: 4 | Q60: =SUM( IFERROR(VLOOKUP(E60,MATERIAUX!$A$1:$D$27,4,FALSE)*F60,0), IFERROR(VLOOKUP(G60,MATERIAUX!$A$1:$D$27,4,FALSE)*H60,0), IFERROR(VLOOKUP(I60,MATERIAUX!$A$1:$D$27,4,FALSE)*J60,0), IFERROR(VLOOKUP(K60,MATERIAUX!$A$1:$D$27,4,FALSE)*L60,0), IFERROR(VLOOKUP(M60,MATERIAUX!$A$1:$D$27,4,FALSE)*N60,0), IFERROR(VLOOKUP(O60,MATERIAUX!$A$1:$D$27,4,FALSE)*P60,0) ) -> 1.3333333
A61: Toque de cuisinier | B61: 20 | C61: =B61-Q61 -> 19.333333 | D61: =(C61/Q61) -> 29 | E61: Fil | F61: 2 | Q61: =SUM( IFERROR(VLOOKUP(E61,MATERIAUX!$A$1:$D$27,4,FALSE)*F61,0), IFERROR(VLOOKUP(G61,MATERIAUX!$A$1:$D$27,4,FALSE)*H61,0), IFERROR(VLOOKUP(I61,MATERIAUX!$A$1:$D$27,4,FALSE)*J61,0), IFERROR(VLOOKUP(K61,MATERIAUX!$A$1:$D$27,4,FALSE)*L61,0), IFERROR(VLOOKUP(M61,MATERIAUX!$A$1:$D$27,4,FALSE)*N61,0), IFERROR(VLOOKUP(O61,MATERIAUX!$A$1:$D$27,4,FALSE)*P61,0) ) -> 0.66666667
A62: Robe de fille (Gris, Bleu, Jaune, Rouge, Vert) | B62: 10 | C62: =B62-Q62 -> 9.3333333 | D62: =(C62/Q62) -> 14 | E62: Fil | F62: 2 | Q62: =SUM( IFERROR(VLOOKUP(E62,MATERIAUX!$A$1:$D$27,4,FALSE)*F62,0), IFERROR(VLOOKUP(G62,MATERIAUX!$A$1:$D$27,4,FALSE)*H62,0), IFERROR(VLOOKUP(I62,MATERIAUX!$A$1:$D$27,4,FALSE)*J62,0), IFERROR(VLOOKUP(K62,MATERIAUX!$A$1:$D$27,4,FALSE)*L62,0), IFERROR(VLOOKUP(M62,MATERIAUX!$A$1:$D$27,4,FALSE)*N62,0), IFERROR(VLOOKUP(O62,MATERIAUX!$A$1:$D$27,4,FALSE)*P62,0) ) -> 0.66666667
A63: Tunique de garçon (Bleu, Gris, Jaune, Rouge, Vert) | B63: 10 | C63: =B63-Q63 -> 9.3333333 | D63: =(C63/Q63) -> 14 | E63: Fil | F63: 2 | Q63: =SUM( IFERROR(VLOOKUP(E63,MATERIAUX!$A$1:$D$27,4,FALSE)*F63,0), IFERROR(VLOOKUP(G63,MATERIAUX!$A$1:$D$27,4,FALSE)*H63,0), IFERROR(VLOOKUP(I63,MATERIAUX!$A$1:$D$27,4,FALSE)*J63,0), IFERROR(VLOOKUP(K63,MATERIAUX!$A$1:$D$27,4,FALSE)*L63,0), IFERROR(VLOOKUP(M63,MATERIAUX!$A$1:$D$27,4,FALSE)*N63,0), IFERROR(VLOOKUP(O63,MATERIAUX!$A$1:$D$27,4,FALSE)*P63,0) ) -> 0.66666667
A64: Exquisite Cloak (Rouge, Noir) | B64: 200 | C64: =B64-Q64 -> 96.666667 | D64: =(C64/Q64) -> 0.93548387 | E64: Fil | F64: 10 | G64: Vif Argent | H64: 2 | Q64: =SUM( IFERROR(VLOOKUP(E64,MATERIAUX!$A$1:$D$27,4,FALSE)*F64,0), IFERROR(VLOOKUP(G64,MATERIAUX!$A$1:$D$27,4,FALSE)*H64,0), IFERROR(VLOOKUP(I64,MATERIAUX!$A$1:$D$27,4,FALSE)*J64,0), IFERROR(VLOOKUP(K64,MATERIAUX!$A$1:$D$27,4,FALSE)*L64,0), IFERROR(VLOOKUP(M64,MATERIAUX!$A$1:$D$27,4,FALSE)*N64,0), IFERROR(VLOOKUP(O64,MATERIAUX!$A$1:$D$27,4,FALSE)*P64,0) ) -> 103.33333
A65: Exquisite Cloak (Vert, Blanc) | B65: 100 | C65: =B65-Q65 -> 76.666667 | D65: =(C65/Q65) -> 3.2857143 | E65: Fil | F65: 10 | G65: Or | H65: 2 | Q65: =SUM( IFERROR(VLOOKUP(E65,MATERIAUX!$A$1:$D$27,4,FALSE)*F65,0), IFERROR(VLOOKUP(G65,MATERIAUX!$A$1:$D$27,4,FALSE)*H65,0), IFERROR(VLOOKUP(I65,MATERIAUX!$A$1:$D$27,4,FALSE)*J65,0), IFERROR(VLOOKUP(K65,MATERIAUX!$A$1:$D$27,4,FALSE)*L65,0), IFERROR(VLOOKUP(M65,MATERIAUX!$A$1:$D$27,4,FALSE)*N65,0), IFERROR(VLOOKUP(O65,MATERIAUX!$A$1:$D$27,4,FALSE)*P65,0) ) -> 23.333333
A66: Fastened Scarf | B66: 20 | C66: =B66-Q66 -> 16.666667 | D66: =(C66/Q66) -> 5 | E66: Fil | F66: 10 | Q66: =SUM( IFERROR(VLOOKUP(E66,MATERIAUX!$A$1:$D$27,4,FALSE)*F66,0), IFERROR(VLOOKUP(G66,MATERIAUX!$A$1:$D$27,4,FALSE)*H66,0), IFERROR(VLOOKUP(I66,MATERIAUX!$A$1:$D$27,4,FALSE)*J66,0), IFERROR(VLOOKUP(K66,MATERIAUX!$A$1:$D$27,4,FALSE)*L66,0), IFERROR(VLOOKUP(M66,MATERIAUX!$A$1:$D$27,4,FALSE)*N66,0), IFERROR(VLOOKUP(O66,MATERIAUX!$A$1:$D$27,4,FALSE)*P66,0) ) -> 3.3333333
A67: Gathered Scarf | B67: 20 | C67: =B67-Q67 -> 13.666667 | D67: =(C67/Q67) -> 2.1578947 | E67: Fil | F67: 10 | G67: Fer | H67: 1 | Q67: =SUM( IFERROR(VLOOKUP(E67,MATERIAUX!$A$1:$D$27,4,FALSE)*F67,0), IFERROR(VLOOKUP(G67,MATERIAUX!$A$1:$D$27,4,FALSE)*H67,0), IFERROR(VLOOKUP(I67,MATERIAUX!$A$1:$D$27,4,FALSE)*J67,0), IFERROR(VLOOKUP(K67,MATERIAUX!$A$1:$D$27,4,FALSE)*L67,0), IFERROR(VLOOKUP(M67,MATERIAUX!$A$1:$D$27,4,FALSE)*N67,0), IFERROR(VLOOKUP(O67,MATERIAUX!$A$1:$D$27,4,FALSE)*P67,0) ) -> 6.3333333
A68: Loose Neck Gaiter Noir | B68: 20 | C68: =B68-Q68 -> 15.916667 | D68: =(C68/Q68) -> 3.8979592 | E68: Fil | F68: 10 | G68: Bandes de cuir | H68: 1 | Q68: =SUM( IFERROR(VLOOKUP(E68,MATERIAUX!$A$1:$D$27,4,FALSE)*F68,0), IFERROR(VLOOKUP(G68,MATERIAUX!$A$1:$D$27,4,FALSE)*H68,0), IFERROR(VLOOKUP(I68,MATERIAUX!$A$1:$D$27,4,FALSE)*J68,0), IFERROR(VLOOKUP(K68,MATERIAUX!$A$1:$D$27,4,FALSE)*L68,0), IFERROR(VLOOKUP(M68,MATERIAUX!$A$1:$D$27,4,FALSE)*N68,0), IFERROR(VLOOKUP(O68,MATERIAUX!$A$1:$D$27,4,FALSE)*P68,0) ) -> 4.0833333
A69: Loose Neck Gaiter Blanc et Gris | B69: 20 | C69: =B69-Q69 -> 15.166667 | D69: =(C69/Q69) -> 3.137931 | E69: Fil | F69: 10 | G69: Bandes de cuir | H69: 2 | Q69: =SUM( IFERROR(VLOOKUP(E69,MATERIAUX!$A$1:$D$27,4,FALSE)*F69,0), IFERROR(VLOOKUP(G69,MATERIAUX!$A$1:$D$27,4,FALSE)*H69,0), IFERROR(VLOOKUP(I69,MATERIAUX!$A$1:$D$27,4,FALSE)*J69,0), IFERROR(VLOOKUP(K69,MATERIAUX!$A$1:$D$27,4,FALSE)*L69,0), IFERROR(VLOOKUP(M69,MATERIAUX!$A$1:$D$27,4,FALSE)*N69,0), IFERROR(VLOOKUP(O69,MATERIAUX!$A$1:$D$27,4,FALSE)*P69,0) ) -> 4.8333333
A70: Patchwork Satchel | B70: 20 | C70: =B70-Q70 -> 16.666667 | D70: =(C70/Q70) -> 5 | E70: Fil | F70: 10 | Q70: =SUM( IFERROR(VLOOKUP(E70,MATERIAUX!$A$1:$D$27,4,FALSE)*F70,0), IFERROR(VLOOKUP(G70,MATERIAUX!$A$1:$D$27,4,FALSE)*H70,0), IFERROR(VLOOKUP(I70,MATERIAUX!$A$1:$D$27,4,FALSE)*J70,0), IFERROR(VLOOKUP(K70,MATERIAUX!$A$1:$D$27,4,FALSE)*L70,0), IFERROR(VLOOKUP(M70,MATERIAUX!$A$1:$D$27,4,FALSE)*N70,0), IFERROR(VLOOKUP(O70,MATERIAUX!$A$1:$D$27,4,FALSE)*P70,0) ) -> 3.3333333
A71: Quilted Mantle | B71: 20 | C71: =B71-Q71 -> 12.166667 | D71: =(C71/Q71) -> 1.5531915 | E71: Fil | F71: 10 | G71: Bandes de cuir | H71: 2 | I71: Fer | J71: 1 | Q71: =SUM( IFERROR(VLOOKUP(E71,MATERIAUX!$A$1:$D$27,4,FALSE)*F71,0), IFERROR(VLOOKUP(G71,MATERIAUX!$A$1:$D$27,4,FALSE)*H71,0), IFERROR(VLOOKUP(I71,MATERIAUX!$A$1:$D$27,4,FALSE)*J71,0), IFERROR(VLOOKUP(K71,MATERIAUX!$A$1:$D$27,4,FALSE)*L71,0), IFERROR(VLOOKUP(M71,MATERIAUX!$A$1:$D$27,4,FALSE)*N71,0), IFERROR(VLOOKUP(O71,MATERIAUX!$A$1:$D$27,4,FALSE)*P71,0) ) -> 7.8333333
A72: Reinforced Backpack Marron foncé | B72: 80 | C72: =B72-Q72 -> 58.416667 | D72: =(C72/Q72) -> 2.7065637 | E72: Fil | F72: 10 | G72: Bandes de cuir | H72: 3 | I72: Cuir | J72: 2 | K72: Corindon raffiné | L72: 1 | Q72: =SUM( IFERROR(VLOOKUP(E72,MATERIAUX!$A$1:$D$27,4,FALSE)*F72,0), IFERROR(VLOOKUP(G72,MATERIAUX!$A$1:$D$27,4,FALSE)*H72,0), IFERROR(VLOOKUP(I72,MATERIAUX!$A$1:$D$27,4,FALSE)*J72,0), IFERROR(VLOOKUP(K72,MATERIAUX!$A$1:$D$27,4,FALSE)*L72,0), IFERROR(VLOOKUP(M72,MATERIAUX!$A$1:$D$27,4,FALSE)*N72,0), IFERROR(VLOOKUP(O72,MATERIAUX!$A$1:$D$27,4,FALSE)*P72,0) ) -> 21.583333
A73: Reinforced Backpack Marron clair | B73: 80 | C73: =B73-Q73 -> 58 | D73: =(C73/Q73) -> 2.6363636 | E73: Cuir | F73: 3 | G73: Bandes de cuir | H73: 4 | I73: Corindon raffiné | J73: 1 | Q73: =SUM( IFERROR(VLOOKUP(E73,MATERIAUX!$A$1:$D$27,4,FALSE)*F73,0), IFERROR(VLOOKUP(G73,MATERIAUX!$A$1:$D$27,4,FALSE)*H73,0), IFERROR(VLOOKUP(I73,MATERIAUX!$A$1:$D$27,4,FALSE)*J73,0), IFERROR(VLOOKUP(K73,MATERIAUX!$A$1:$D$27,4,FALSE)*L73,0), IFERROR(VLOOKUP(M73,MATERIAUX!$A$1:$D$27,4,FALSE)*N73,0), IFERROR(VLOOKUP(O73,MATERIAUX!$A$1:$D$27,4,FALSE)*P73,0) ) -> 22
A74: Reinforced Backpack Gris et Gris foncé | B74: 80 | C74: =B74-Q74 -> 65.416667 | D74: =(C74/Q74) -> 4.4857143 | E74: Fil | F74: 10 | G74: Bandes de cuir | H74: 3 | I74: Cuir | J74: 2 | K74: Fer | L74: 1 | Q74: =SUM( IFERROR(VLOOKUP(E74,MATERIAUX!$A$1:$D$27,4,FALSE)*F74,0), IFERROR(VLOOKUP(G74,MATERIAUX!$A$1:$D$27,4,FALSE)*H74,0), IFERROR(VLOOKUP(I74,MATERIAUX!$A$1:$D$27,4,FALSE)*J74,0), IFERROR(VLOOKUP(K74,MATERIAUX!$A$1:$D$27,4,FALSE)*L74,0), IFERROR(VLOOKUP(M74,MATERIAUX!$A$1:$D$27,4,FALSE)*N74,0), IFERROR(VLOOKUP(O74,MATERIAUX!$A$1:$D$27,4,FALSE)*P74,0) ) -> 14.583333
A75: Reinforced Backpack & Lantern Gris | B75: 90 | C75: =B75-Q75 -> 60 | D75: =(C75/Q75) -> 2 | E75: Cuir | F75: 3 | G75: Bandes de cuir | H75: 4 | I75: Petit bois | J75: 2 | K75: Corindon raffiné | L75: 1 | M75: Fer | N75: 2 | Q75: =SUM( IFERROR(VLOOKUP(E75,MATERIAUX!$A$1:$D$27,4,FALSE)*F75,0), IFERROR(VLOOKUP(G75,MATERIAUX!$A$1:$D$27,4,FALSE)*H75,0), IFERROR(VLOOKUP(I75,MATERIAUX!$A$1:$D$27,4,FALSE)*J75,0), IFERROR(VLOOKUP(K75,MATERIAUX!$A$1:$D$27,4,FALSE)*L75,0), IFERROR(VLOOKUP(M75,MATERIAUX!$A$1:$D$27,4,FALSE)*N75,0), IFERROR(VLOOKUP(O75,MATERIAUX!$A$1:$D$27,4,FALSE)*P75,0) ) -> 30
A76: Reinforced Backpack & Lantern Marron et Noir | B76: 90 | C76: =B76-Q76 -> 67.416667 | D76: =(C76/Q76) -> 2.9852399 | E76: Fil | F76: 10 | G76: Bandes de cuir | H76: 3 | I76: Cuir | J76: 2 | K76: Petit bois | L76: 2 | M76: Fer | N76: 3 | Q76: =SUM( IFERROR(VLOOKUP(E76,MATERIAUX!$A$1:$D$27,4,FALSE)*F76,0), IFERROR(VLOOKUP(G76,MATERIAUX!$A$1:$D$27,4,FALSE)*H76,0), IFERROR(VLOOKUP(I76,MATERIAUX!$A$1:$D$27,4,FALSE)*J76,0), IFERROR(VLOOKUP(K76,MATERIAUX!$A$1:$D$27,4,FALSE)*L76,0), IFERROR(VLOOKUP(M76,MATERIAUX!$A$1:$D$27,4,FALSE)*N76,0), IFERROR(VLOOKUP(O76,MATERIAUX!$A$1:$D$27,4,FALSE)*P76,0) ) -> 22.583333
A77: Reinforced Backpack & Lantern Marron Foncé | B77: 90 | C77: =B77-Q77 -> 70.416667 | D77: =(C77/Q77) -> 3.5957447 | E77: Fil | F77: 10 | G77: Cuir | H77: 2 | I77: Bandes de cuir | J77: 3 | K77: Petit bois | L77: 2 | M77: Fer | N77: 2 | Q77: =SUM( IFERROR(VLOOKUP(E77,MATERIAUX!$A$1:$D$27,4,FALSE)*F77,0), IFERROR(VLOOKUP(G77,MATERIAUX!$A$1:$D$27,4,FALSE)*H77,0), IFERROR(VLOOKUP(I77,MATERIAUX!$A$1:$D$27,4,FALSE)*J77,0), IFERROR(VLOOKUP(K77,MATERIAUX!$A$1:$D$27,4,FALSE)*L77,0), IFERROR(VLOOKUP(M77,MATERIAUX!$A$1:$D$27,4,FALSE)*N77,0), IFERROR(VLOOKUP(O77,MATERIAUX!$A$1:$D$27,4,FALSE)*P77,0) ) -> 19.583333
A78: Reinforced Mantle | B78: 20 | C78: =B78-Q78 -> 12.166667 | D78: =(C78/Q78) -> 1.5531915 | E78: Fil | F78: 10 | G78: Bandes de cuir | H78: 2 | I78: Fer | J78: 1 | Q78: =SUM( IFERROR(VLOOKUP(E78,MATERIAUX!$A$1:$D$27,4,FALSE)*F78,0), IFERROR(VLOOKUP(G78,MATERIAUX!$A$1:$D$27,4,FALSE)*H78,0), IFERROR(VLOOKUP(I78,MATERIAUX!$A$1:$D$27,4,FALSE)*J78,0), IFERROR(VLOOKUP(K78,MATERIAUX!$A$1:$D$27,4,FALSE)*L78,0), IFERROR(VLOOKUP(M78,MATERIAUX!$A$1:$D$27,4,FALSE)*N78,0), IFERROR(VLOOKUP(O78,MATERIAUX!$A$1:$D$27,4,FALSE)*P78,0) ) -> 7.8333333
A79: Reinforced Satchel | B79: 40 | C79: =B79-Q79 -> 21.75 | D79: =(C79/Q79) -> 1.1917808 | E79: Cuir | F79: 2 | G79: Bandes de cuir | H79: 3 | I79: Or | J79: 1 | Q79: =SUM( IFERROR(VLOOKUP(E79,MATERIAUX!$A$1:$D$27,4,FALSE)*F79,0), IFERROR(VLOOKUP(G79,MATERIAUX!$A$1:$D$27,4,FALSE)*H79,0), IFERROR(VLOOKUP(I79,MATERIAUX!$A$1:$D$27,4,FALSE)*J79,0), IFERROR(VLOOKUP(K79,MATERIAUX!$A$1:$D$27,4,FALSE)*L79,0), IFERROR(VLOOKUP(M79,MATERIAUX!$A$1:$D$27,4,FALSE)*N79,0), IFERROR(VLOOKUP(O79,MATERIAUX!$A$1:$D$27,4,FALSE)*P79,0) ) -> 18.25
A80: Rugged Cape | B80: 20 | C80: =B80-Q80 -> 16.666667 | D80: =(C80/Q80) -> 5 | E80: Fil | F80: 10 | Q80: =SUM( IFERROR(VLOOKUP(E80,MATERIAUX!$A$1:$D$27,4,FALSE)*F80,0), IFERROR(VLOOKUP(G80,MATERIAUX!$A$1:$D$27,4,FALSE)*H80,0), IFERROR(VLOOKUP(I80,MATERIAUX!$A$1:$D$27,4,FALSE)*J80,0), IFERROR(VLOOKUP(K80,MATERIAUX!$A$1:$D$27,4,FALSE)*L80,0), IFERROR(VLOOKUP(M80,MATERIAUX!$A$1:$D$27,4,FALSE)*N80,0), IFERROR(VLOOKUP(O80,MATERIAUX!$A$1:$D$27,4,FALSE)*P80,0) ) -> 3.3333333
A81: Rugged Mask | B81: 20 | C81: =B81-Q81 -> 18.333333 | D81: =(C81/Q81) -> 11 | E81: Fil | F81: 5 | Q81: =SUM( IFERROR(VLOOKUP(E81,MATERIAUX!$A$1:$D$27,4,FALSE)*F81,0), IFERROR(VLOOKUP(G81,MATERIAUX!$A$1:$D$27,4,FALSE)*H81,0), IFERROR(VLOOKUP(I81,MATERIAUX!$A$1:$D$27,4,FALSE)*J81,0), IFERROR(VLOOKUP(K81,MATERIAUX!$A$1:$D$27,4,FALSE)*L81,0), IFERROR(VLOOKUP(M81,MATERIAUX!$A$1:$D$27,4,FALSE)*N81,0), IFERROR(VLOOKUP(O81,MATERIAUX!$A$1:$D$27,4,FALSE)*P81,0) ) -> 1.6666667
A82: Short Cloth Cape | B82: 20 | C82: =B82-Q82 -> 13.666667 | D82: =(C82/Q82) -> 2.1578947 | E82: Fil | F82: 10 | G82: Fer | H82: 1 | Q82: =SUM( IFERROR(VLOOKUP(E82,MATERIAUX!$A$1:$D$27,4,FALSE)*F82,0), IFERROR(VLOOKUP(G82,MATERIAUX!$A$1:$D$27,4,FALSE)*H82,0), IFERROR(VLOOKUP(I82,MATERIAUX!$A$1:$D$27,4,FALSE)*J82,0), IFERROR(VLOOKUP(K82,MATERIAUX!$A$1:$D$27,4,FALSE)*L82,0), IFERROR(VLOOKUP(M82,MATERIAUX!$A$1:$D$27,4,FALSE)*N82,0), IFERROR(VLOOKUP(O82,MATERIAUX!$A$1:$D$27,4,FALSE)*P82,0) ) -> 6.3333333
A83: Short Woven Scarf | B83: 20 | C83: =B83-Q83 -> 16.666667 | D83: =(C83/Q83) -> 5 | E83: Fil | F83: 10 | Q83: =SUM( IFERROR(VLOOKUP(E83,MATERIAUX!$A$1:$D$27,4,FALSE)*F83,0), IFERROR(VLOOKUP(G83,MATERIAUX!$A$1:$D$27,4,FALSE)*H83,0), IFERROR(VLOOKUP(I83,MATERIAUX!$A$1:$D$27,4,FALSE)*J83,0), IFERROR(VLOOKUP(K83,MATERIAUX!$A$1:$D$27,4,FALSE)*L83,0), IFERROR(VLOOKUP(M83,MATERIAUX!$A$1:$D$27,4,FALSE)*N83,0), IFERROR(VLOOKUP(O83,MATERIAUX!$A$1:$D$27,4,FALSE)*P83,0) ) -> 3.3333333
A84: Sturdy Pouch (Left, Right) | B84: 40 | C84: =B84-Q84 -> 27.583333 | D84: =(C84/Q84) -> 2.2214765 | E84: Fil | F84: 5 | G84: Bandes de cuir | H84: 1 | I84: Or | J84: 1 | Q84: =SUM( IFERROR(VLOOKUP(E84,MATERIAUX!$A$1:$D$27,4,FALSE)*F84,0), IFERROR(VLOOKUP(G84,MATERIAUX!$A$1:$D$27,4,FALSE)*H84,0), IFERROR(VLOOKUP(I84,MATERIAUX!$A$1:$D$27,4,FALSE)*J84,0), IFERROR(VLOOKUP(K84,MATERIAUX!$A$1:$D$27,4,FALSE)*L84,0), IFERROR(VLOOKUP(M84,MATERIAUX!$A$1:$D$27,4,FALSE)*N84,0), IFERROR(VLOOKUP(O84,MATERIAUX!$A$1:$D$27,4,FALSE)*P84,0) ) -> 12.416667
A85: Sturdy Pouch (Left, Right) | B85: 100 | C85: =B85-Q85 -> 47.583333 | D85: =(C85/Q85) -> 0.90779014 | E85: Fil | F85: 5 | G85: Bandes de cuir | H85: 1 | I85: Vif Argent | J85: 1 | Q85: =SUM( IFERROR(VLOOKUP(E85,MATERIAUX!$A$1:$D$27,4,FALSE)*F85,0), IFERROR(VLOOKUP(G85,MATERIAUX!$A$1:$D$27,4,FALSE)*H85,0), IFERROR(VLOOKUP(I85,MATERIAUX!$A$1:$D$27,4,FALSE)*J85,0), IFERROR(VLOOKUP(K85,MATERIAUX!$A$1:$D$27,4,FALSE)*L85,0), IFERROR(VLOOKUP(M85,MATERIAUX!$A$1:$D$27,4,FALSE)*N85,0), IFERROR(VLOOKUP(O85,MATERIAUX!$A$1:$D$27,4,FALSE)*P85,0) ) -> 52.416667
A86: Toothlock Satchel | B86: 50 | C86: =B86-Q86 -> 43.833333 | D86: =(C86/Q86) -> 7.1081081 | E86: Fil | F86: 5 | G86: Bandes de cuir | H86: 2 | I86: Dent de smilodon | J86: 1 | Q86: =SUM( IFERROR(VLOOKUP(E86,MATERIAUX!$A$1:$D$27,4,FALSE)*F86,0), IFERROR(VLOOKUP(G86,MATERIAUX!$A$1:$D$27,4,FALSE)*H86,0), IFERROR(VLOOKUP(I86,MATERIAUX!$A$1:$D$27,4,FALSE)*J86,0), IFERROR(VLOOKUP(K86,MATERIAUX!$A$1:$D$27,4,FALSE)*L86,0), IFERROR(VLOOKUP(M86,MATERIAUX!$A$1:$D$27,4,FALSE)*N86,0), IFERROR(VLOOKUP(O86,MATERIAUX!$A$1:$D$27,4,FALSE)*P86,0) ) -> 6.1666667
A87: Trader's Resource | B87: 80 | C87: =B87-Q87 -> 67.333333 | D87: =(C87/Q87) -> 5.3157895 | E87: Fil | F87: 5 | G87: Bandes de cuir | H87: 4 | I87: Petit bois | J87: 2 | K87: Fer | L87: 2 | Q87: =SUM( IFERROR(VLOOKUP(E87,MATERIAUX!$A$1:$D$27,4,FALSE)*F87,0), IFERROR(VLOOKUP(G87,MATERIAUX!$A$1:$D$27,4,FALSE)*H87,0), IFERROR(VLOOKUP(I87,MATERIAUX!$A$1:$D$27,4,FALSE)*J87,0), IFERROR(VLOOKUP(K87,MATERIAUX!$A$1:$D$27,4,FALSE)*L87,0), IFERROR(VLOOKUP(M87,MATERIAUX!$A$1:$D$27,4,FALSE)*N87,0), IFERROR(VLOOKUP(O87,MATERIAUX!$A$1:$D$27,4,FALSE)*P87,0) ) -> 12.666667
A88: Trader's Resource & Lantern | B88: 80 | C88: =B88-Q88 -> 60.333333 | D88: =(C88/Q88) -> 3.0677966 | E88: Fil | F88: 5 | G88: Bandes de cuir | H88: 4 | I88: Petit bois | J88: 3 | K88: Fer | L88: 4 | Q88: =SUM( IFERROR(VLOOKUP(E88,MATERIAUX!$A$1:$D$27,4,FALSE)*F88,0), IFERROR(VLOOKUP(G88,MATERIAUX!$A$1:$D$27,4,FALSE)*H88,0), IFERROR(VLOOKUP(I88,MATERIAUX!$A$1:$D$27,4,FALSE)*J88,0), IFERROR(VLOOKUP(K88,MATERIAUX!$A$1:$D$27,4,FALSE)*L88,0), IFERROR(VLOOKUP(M88,MATERIAUX!$A$1:$D$27,4,FALSE)*N88,0), IFERROR(VLOOKUP(O88,MATERIAUX!$A$1:$D$27,4,FALSE)*P88,0) ) -> 19.666667
C89: =B89-Q89 -> 0 | D89: =(C89/Q89) -> #DIV/0! | Q89: =SUM( IFERROR(VLOOKUP(E89,MATERIAUX!$A$1:$D$27,4,FALSE)*F89,0), IFERROR(VLOOKUP(G89,MATERIAUX!$A$1:$D$27,4,FALSE)*H89,0), IFERROR(VLOOKUP(I89,MATERIAUX!$A$1:$D$27,4,FALSE)*J89,0), IFERROR(VLOOKUP(K89,MATERIAUX!$A$1:$D$27,4,FALSE)*L89,0), IFERROR(VLOOKUP(M89,MATERIAUX!$A$1:$D$27,4,FALSE)*N89,0), IFERROR(VLOOKUP(O89,MATERIAUX!$A$1:$D$27,4,FALSE)*P89,0) ) -> 0
C90: =B90-Q90 -> 0 | D90: =(C90/Q90) -> #DIV/0! | Q90: =SUM( IFERROR(VLOOKUP(E90,MATERIAUX!$A$1:$D$27,4,FALSE)*F90,0), IFERROR(VLOOKUP(G90,MATERIAUX!$A$1:$D$27,4,FALSE)*H90,0), IFERROR(VLOOKUP(I90,MATERIAUX!$A$1:$D$27,4,FALSE)*J90,0), IFERROR(VLOOKUP(K90,MATERIAUX!$A$1:$D$27,4,FALSE)*L90,0), IFERROR(VLOOKUP(M90,MATERIAUX!$A$1:$D$27,4,FALSE)*N90,0), IFERROR(VLOOKUP(O90,MATERIAUX!$A$1:$D$27,4,FALSE)*P90,0) ) -> 0
C91: =B91-Q91 -> 0 | D91: =(C91/Q91) -> #DIV/0! | Q91: =SUM( IFERROR(VLOOKUP(E91,MATERIAUX!$A$1:$D$27,4,FALSE)*F91,0), IFERROR(VLOOKUP(G91,MATERIAUX!$A$1:$D$27,4,FALSE)*H91,0), IFERROR(VLOOKUP(I91,MATERIAUX!$A$1:$D$27,4,FALSE)*J91,0), IFERROR(VLOOKUP(K91,MATERIAUX!$A$1:$D$27,4,FALSE)*L91,0), IFERROR(VLOOKUP(M91,MATERIAUX!$A$1:$D$27,4,FALSE)*N91,0), IFERROR(VLOOKUP(O91,MATERIAUX!$A$1:$D$27,4,FALSE)*P91,0) ) -> 0
C92: =B92-Q92 -> 0 | D92: =(C92/Q92) -> #DIV/0! | Q92: =SUM( IFERROR(VLOOKUP(E92,MATERIAUX!$A$1:$D$27,4,FALSE)*F92,0), IFERROR(VLOOKUP(G92,MATERIAUX!$A$1:$D$27,4,FALSE)*H92,0), IFERROR(VLOOKUP(I92,MATERIAUX!$A$1:$D$27,4,FALSE)*J92,0), IFERROR(VLOOKUP(K92,MATERIAUX!$A$1:$D$27,4,FALSE)*L92,0), IFERROR(VLOOKUP(M92,MATERIAUX!$A$1:$D$27,4,FALSE)*N92,0), IFERROR(VLOOKUP(O92,MATERIAUX!$A$1:$D$27,4,FALSE)*P92,0) ) -> 0
C93: =B93-Q93 -> 0 | D93: =(C93/Q93) -> #DIV/0! | Q93: =SUM( IFERROR(VLOOKUP(E93,MATERIAUX!$A$1:$D$27,4,FALSE)*F93,0), IFERROR(VLOOKUP(G93,MATERIAUX!$A$1:$D$27,4,FALSE)*H93,0), IFERROR(VLOOKUP(I93,MATERIAUX!$A$1:$D$27,4,FALSE)*J93,0), IFERROR(VLOOKUP(K93,MATERIAUX!$A$1:$D$27,4,FALSE)*L93,0), IFERROR(VLOOKUP(M93,MATERIAUX!$A$1:$D$27,4,FALSE)*N93,0), IFERROR(VLOOKUP(O93,MATERIAUX!$A$1:$D$27,4,FALSE)*P93,0) ) -> 0
C94: =B94-Q94 -> 0 | D94: =(C94/Q94) -> #DIV/0! | Q94: =SUM( IFERROR(VLOOKUP(E94,MATERIAUX!$A$1:$D$27,4,FALSE)*F94,0), IFERROR(VLOOKUP(G94,MATERIAUX!$A$1:$D$27,4,FALSE)*H94,0), IFERROR(VLOOKUP(I94,MATERIAUX!$A$1:$D$27,4,FALSE)*J94,0), IFERROR(VLOOKUP(K94,MATERIAUX!$A$1:$D$27,4,FALSE)*L94,0), IFERROR(VLOOKUP(M94,MATERIAUX!$A$1:$D$27,4,FALSE)*N94,0), IFERROR(VLOOKUP(O94,MATERIAUX!$A$1:$D$27,4,FALSE)*P94,0) ) -> 0
C95: =B95-Q95 -> 0 | D95: =(C95/Q95) -> #DIV/0! | Q95: =SUM( IFERROR(VLOOKUP(E95,MATERIAUX!$A$1:$D$27,4,FALSE)*F95,0), IFERROR(VLOOKUP(G95,MATERIAUX!$A$1:$D$27,4,FALSE)*H95,0), IFERROR(VLOOKUP(I95,MATERIAUX!$A$1:$D$27,4,FALSE)*J95,0), IFERROR(VLOOKUP(K95,MATERIAUX!$A$1:$D$27,4,FALSE)*L95,0), IFERROR(VLOOKUP(M95,MATERIAUX!$A$1:$D$27,4,FALSE)*N95,0), IFERROR(VLOOKUP(O95,MATERIAUX!$A$1:$D$27,4,FALSE)*P95,0) ) -> 0
C96: =B96-Q96 -> 0 | D96: =(C96/Q96) -> #DIV/0! | Q96: =SUM( IFERROR(VLOOKUP(E96,MATERIAUX!$A$1:$D$27,4,FALSE)*F96,0), IFERROR(VLOOKUP(G96,MATERIAUX!$A$1:$D$27,4,FALSE)*H96,0), IFERROR(VLOOKUP(I96,MATERIAUX!$A$1:$D$27,4,FALSE)*J96,0), IFERROR(VLOOKUP(K96,MATERIAUX!$A$1:$D$27,4,FALSE)*L96,0), IFERROR(VLOOKUP(M96,MATERIAUX!$A$1:$D$27,4,FALSE)*N96,0), IFERROR(VLOOKUP(O96,MATERIAUX!$A$1:$D$27,4,FALSE)*P96,0) ) -> 0
C97: =B97-Q97 -> 0 | D97: =(C97/Q97) -> #DIV/0! | Q97: =SUM( IFERROR(VLOOKUP(E97,MATERIAUX!$A$1:$D$27,4,FALSE)*F97,0), IFERROR(VLOOKUP(G97,MATERIAUX!$A$1:$D$27,4,FALSE)*H97,0), IFERROR(VLOOKUP(I97,MATERIAUX!$A$1:$D$27,4,FALSE)*J97,0), IFERROR(VLOOKUP(K97,MATERIAUX!$A$1:$D$27,4,FALSE)*L97,0), IFERROR(VLOOKUP(M97,MATERIAUX!$A$1:$D$27,4,FALSE)*N97,0), IFERROR(VLOOKUP(O97,MATERIAUX!$A$1:$D$27,4,FALSE)*P97,0) ) -> 0
C98: =B98-Q98 -> 0 | D98: =(C98/Q98) -> #DIV/0! | Q98: =SUM( IFERROR(VLOOKUP(E98,MATERIAUX!$A$1:$D$27,4,FALSE)*F98,0), IFERROR(VLOOKUP(G98,MATERIAUX!$A$1:$D$27,4,FALSE)*H98,0), IFERROR(VLOOKUP(I98,MATERIAUX!$A$1:$D$27,4,FALSE)*J98,0), IFERROR(VLOOKUP(K98,MATERIAUX!$A$1:$D$27,4,FALSE)*L98,0), IFERROR(VLOOKUP(M98,MATERIAUX!$A$1:$D$27,4,FALSE)*N98,0), IFERROR(VLOOKUP(O98,MATERIAUX!$A$1:$D$27,4,FALSE)*P98,0) ) -> 0
C99: =B99-Q99 -> 0 | D99: =(C99/Q99) -> #DIV/0! | Q99: =SUM( IFERROR(VLOOKUP(E99,MATERIAUX!$A$1:$D$27,4,FALSE)*F99,0), IFERROR(VLOOKUP(G99,MATERIAUX!$A$1:$D$27,4,FALSE)*H99,0), IFERROR(VLOOKUP(I99,MATERIAUX!$A$1:$D$27,4,FALSE)*J99,0), IFERROR(VLOOKUP(K99,MATERIAUX!$A$1:$D$27,4,FALSE)*L99,0), IFERROR(VLOOKUP(M99,MATERIAUX!$A$1:$D$27,4,FALSE)*N99,0), IFERROR(VLOOKUP(O99,MATERIAUX!$A$1:$D$27,4,FALSE)*P99,0) ) -> 0
C100: =B100-Q100 -> 0 | D100: =(C100/Q100) -> #DIV/0! | Q100: =SUM( IFERROR(VLOOKUP(E100,MATERIAUX!$A$1:$D$27,4,FALSE)*F100,0), IFERROR(VLOOKUP(G100,MATERIAUX!$A$1:$D$27,4,FALSE)*H100,0), IFERROR(VLOOKUP(I100,MATERIAUX!$A$1:$D$27,4,FALSE)*J100,0), IFERROR(VLOOKUP(K100,MATERIAUX!$A$1:$D$27,4,FALSE)*L100,0), IFERROR(VLOOKUP(M100,MATERIAUX!$A$1:$D$27,4,FALSE)*N100,0), IFERROR(VLOOKUP(O100,MATERIAUX!$A$1:$D$27,4,FALSE)*P100,0) ) -> 0
... C117: =B117-Q117 -> 0 | D117: =(C117/Q117) -> #DIV/0! | Q117: =SUM( IFERROR(VLOOKUP(E117,MATERIAUX!$A$1:$D$27,4,FALSE)*F117,0), IFERROR(VLOOKUP(G117,MATERIAUX!$A$1:$D$27,4,FALSE)*H117,0), IFERROR(VLOOKUP(I117,MATERIAUX!$A$1:$D$27,4,FALSE)*J117,0), IFERROR(VLOOKUP(K117,MATERIAUX!$A$1:$D$27,4,FALSE)*L117,0), IFERROR(VLOOKUP(M117,MATERIAUX!$A$1:$D$27,4,FALSE)*N117,0), IFERROR(VLOOKUP(O117,MATERIAUX!$A$1:$D$27,4,FALSE)*P117,0) ) -> 0

Sheet MATERIAUX
A1: Objet | B1: Prix d'achat | C1: Quantitée | D1: Prix à l'unitée
A2: Lys des Cimes | B2: 1 | C2: 15 | D2: =B2/C2 -> 0.066666667
A3: Coton | B3: 1 | C3: 10 | D3: =B3/C3 -> 0.1
A4: Cuir | B4: 3 | C4: 1 | D4: =B4/C4 -> 3
A5: Bandes de cuir | B5: 3 | C5: 4 | D5: =B5/C5 -> 0.75
A6: Fer | B6: 3 | C6: 1 | D6: =B6/C6 -> 3
A7: Or | B7: 10 | C7: 1 | D7: =B7/C7 -> 10
A8: Vif Argent | B8: 50 | C8: 1 | D8: =B8/C8 -> 50
A9: Corindon raffiné | B9: 10 | C9: 1 | D9: =B9/C9 -> 10
A10: Argent | B10: 4 | C10: 1 | D10: =B10/C10 -> 4
A11: Dent de smilodon | B11: 3 | C11: 1 | D11: =B11/C11 -> 3
A12: Petit Bois | B12: 1 | C12: 1 | D12: =B12/C12 -> 1
A13: Fil | B13: 1 | C13: 3 | D13: =B13/C13 -> 0.33333333
A14: Lin | B14: 850 | C14: 1 | D14: =B14/C14 -> 850
